qbodbc/__init__.py
qbodbc/client.py
qbodbc/exceptions.py
qbodbc/utils.py
qbodbc/objects/__init__.py
qbodbc/objects/account.py
qbodbc/objects/address.py
qbodbc/objects/base_object.py
qbodbc/objects/bill.py
qbodbc/objects/customer.py
qbodbc/objects/journal.py
tests/__init__.py
tests/test_base.py
qbodbc-0.0.2.dist-info/LICENSE
qbodbc-0.0.2.dist-info/METADATA
qbodbc-0.0.2.dist-info/WHEEL
qbodbc-0.0.2.dist-info/top_level.txt
qbodbc-0.0.2.dist-info/RECORD
